idelium/__init__.py
idelium/py.typed
idelium/_internal/__init__.py
idelium/_internal/ideliumclib.py
idelium/_internal/ideliummanager.py
idelium/_internal/ideliumserver.py
idelium/_internal/ideliumws.py
idelium/_internal/main.py
idelium/_internal/bdd/__init__.py
idelium/_internal/bdd/bdd.py
idelium/_internal/bdd/webservice.py
idelium/_internal/commons/__init__.py
idelium/_internal/commons/androideventkey.py
idelium/_internal/commons/ideliumprinter.py
idelium/_internal/commons/postmantranslate.py
idelium/_internal/commons/proxy.py
idelium/_internal/commons/resultenum.py
idelium/_internal/commons/seleniumby.py
idelium/_internal/commons/seleniumkeyevent.py
idelium/_internal/extra/__init__.py
idelium/_internal/thirdparties/__init__.py
idelium/_internal/thirdparties/ideliumpostman.py
idelium/_internal/thirdparties/ideliumzephyr.py
idelium/_internal/wrappers/__init__.py
idelium/_internal/wrappers/ideliumappium.py
idelium/_internal/wrappers/ideliumselenium.py
idelium-1.0.10.dist-info/LICENSE.txt
idelium-1.0.10.dist-info/METADATA
idelium-1.0.10.dist-info/WHEEL
idelium-1.0.10.dist-info/entry_points.txt
idelium-1.0.10.dist-info/top_level.txt
idelium-1.0.10.dist-info/RECORD
