Metadata-Version: 2.1
Name: idelium
Version: 1.0.10
Summary: Command line Test Automation Tool
Home-page: https://idelium.io/
Author: Idel Fuschini
Author-email: idel.fuschini@gmail.com
License: MIT
Project-URL: Bug Reports, https://github.com/idelium/idelium-cli/issues
Project-URL: Project, https://idelium.io
Project-URL: Say Thanks!, http://www.idelfuschini.it
Project-URL: Source, https://github.com/idelium/idelium-cli/
Classifier: Development Status :: 5 - Production/Stable
Classifier: Intended Audience :: Developers
Classifier: License :: OSI Approved :: MIT License
Classifier: Topic :: Software Development :: Build Tools
Classifier: Programming Language :: Python
Classifier: Programming Language :: Python :: 3
Classifier: Programming Language :: Python :: 3 :: Only
Classifier: Programming Language :: Python :: 3.7
Classifier: Programming Language :: Python :: 3.8
Classifier: Programming Language :: Python :: 3.9
Classifier: Programming Language :: Python :: 3.10
Classifier: Programming Language :: Python :: 3.11
Classifier: Programming Language :: Python :: Implementation :: CPython
Classifier: Programming Language :: Python :: Implementation :: PyPy
Requires-Python: >=3.7
License-File: LICENSE.txt
Requires-Dist: selenium
Requires-Dist: libmagic
Requires-Dist: Appium-Python-Client
Requires-Dist: webdriver-manager
Requires-Dist: Pillow
Requires-Dist: requests-hawk
Requires-Dist: requests-oauthlib
Requires-Dist: tqdm
Provides-Extra: dev
Requires-Dist: check-manifest ; extra == 'dev'
Provides-Extra: test
Requires-Dist: coverage ; extra == 'test'
